MANIFEST.in
README.txt
setup.py
N2PC_Library/__init__.py
N2PC_Library.egg-info/PKG-INFO
N2PC_Library.egg-info/SOURCES.txt
N2PC_Library.egg-info/dependency_links.txt
N2PC_Library.egg-info/top_level.txt