Metadata-Version: 1.1
Name: N2PC-Library
Version: 0.0.1
Summary: Calculates N2PC component of attention
Home-page: UNKNOWN
Author: Lora Fanda
Author-email: lorafanda7@gmail.com
License: MIT
Keywords: N2PC
Platform: UNKNOWN
Classifier: Development Status :: 5 - Production/Stable
Classifier: Intended Audience :: Education
Classifier: Operating System :: Microsoft :: Windows :: Windows 10
Classifier: License :: OSI Approved :: MIT License
Classifier: Programming Language :: Python :: 3
